{
  "Product name": {
    "$type": "string",
    "$value": "Kale",
    "$description": "",
    "$extensions": {
      "com.figma": {
        "hiddenFromPublishing": false,
        "scopes": [
          "ALL_SCOPES"
        ],
        "codeSyntax": {}
      }
    }
  },
  "Price": {
    "$type": "number",
    "$value": 2.990000009536743,
    "$description": "",
    "$extensions": {
      "com.figma": {
        "hiddenFromPublishing": false,
        "scopes": [
          "TEXT_CONTENT"
        ],
        "codeSyntax": {}
      }
    }
  },
  "Image": {
    "$type": "string",
    "$value": "Kale",
    "$description": "",
    "$extensions": {
      "com.figma": {
        "hiddenFromPublishing": false,
        "scopes": [
          "ALL_SCOPES"
        ],
        "codeSyntax": {}
      }
    }
  },
  "Description": {
    "$type": "string",
    "$value": "Our Ohio-grown kale is a nutritious delight for your taste buds. Grown in the heart of the Buckeye State, this kale is bursting with flavor and has a tender texture that is unmatched. Each leaf is carefully hand-picked to ensure maximum freshness and nutrient density. Whether you enjoy it in a delicious salad, as a side dish, or in your favorite smoothie, this kale is sure to impress. With its deep green color and earthy flavor, our Ohio kale is a must-try for anyone who loves high-quality, locally sourced produce. Plus, it's packed with vitamins and minerals to keep you healthy and energized.",
    "$description": "",
    "$extensions": {
      "com.figma": {
        "hiddenFromPublishing": false,
        "scopes": [
          "ALL_SCOPES"
        ],
        "codeSyntax": {}
      }
    }
  },
  "Farm": {
    "$type": "string",
    "$value": "Bernal Growers",
    "$description": "",
    "$extensions": {
      "com.figma": {
        "hiddenFromPublishing": false,
        "scopes": [
          "ALL_SCOPES"
        ],
        "codeSyntax": {}
      }
    }
  },
  "Location": {
    "$type": "string",
    "$value": "Ohio",
    "$description": "",
    "$extensions": {
      "com.figma": {
        "hiddenFromPublishing": false,
        "scopes": [
          "ALL_SCOPES"
        ],
        "codeSyntax": {}
      }
    }
  },
  "Amount in basket": {
    "$type": "string",
    "$value": "0",
    "$description": "",
    "$extensions": {
      "com.figma": {
        "hiddenFromPublishing": false,
        "scopes": [
          "ALL_SCOPES"
        ],
        "codeSyntax": {}
      }
    }
  },
  "Basket total": {
    "$type": "string",
    "$value": "0",
    "$description": "",
    "$extensions": {
      "com.figma": {
        "hiddenFromPublishing": false,
        "scopes": [
          "ALL_SCOPES"
        ],
        "codeSyntax": {}
      }
    }
  },
  "Theme": {
    "$type": "color",
    "$value": "#7db8a9",
    "$description": "",
    "$extensions": {
      "com.figma": {
        "hiddenFromPublishing": false,
        "scopes": [
          "ALL_SCOPES"
        ],
        "codeSyntax": {}
      }
    }
  },
  "In basket?": {
    "$type": "boolean",
    "$value": false,
    "$description": "",
    "$extensions": {
      "com.figma": {
        "hiddenFromPublishing": false,
        "scopes": [
          "ALL_SCOPES"
        ],
        "codeSyntax": {}
      }
    }
  }
}